Metadata-Version: 2.1
Name: GSLASH
Version: 1.0.0
Summary: This is cython but other rules
Author: GSLASH Development
Classifier: Programming Language :: Python :: 3
Classifier: License :: OSI Approved :: MIT License
Classifier: Operating System :: OS Independent
Requires-Python: >=3.6
